odoo/addons/stock_picking_manual_package/README.rst
odoo/addons/stock_picking_manual_package/__init__.py
odoo/addons/stock_picking_manual_package/__manifest__.py
odoo/addons/stock_picking_manual_package/i18n/es.po
odoo/addons/stock_picking_manual_package/i18n/stock_picking_manual_package.pot
odoo/addons/stock_picking_manual_package/models/__init__.py
odoo/addons/stock_picking_manual_package/models/stock_picking.py
odoo/addons/stock_picking_manual_package/models/stock_quant_package.py
odoo/addons/stock_picking_manual_package/readme/CONTRIBUTORS.rst
odoo/addons/stock_picking_manual_package/readme/DESCRIPTION.rst
odoo/addons/stock_picking_manual_package/readme/USAGE.rst
odoo/addons/stock_picking_manual_package/static/description/icon.png
odoo/addons/stock_picking_manual_package/static/description/index.html
odoo/addons/stock_picking_manual_package/tests/__init__.py
odoo/addons/stock_picking_manual_package/tests/test_stock_picking_manual_package.py
odoo/addons/stock_picking_manual_package/wizards/__init__.py
odoo/addons/stock_picking_manual_package/wizards/stock_picking_manual_package_wiz.py
odoo/addons/stock_picking_manual_package/wizards/stock_picking_manual_package_wizard_view.xml
odoo13_addon_stock_picking_manual_package-13.0.1.1.0.dist-info/METADATA
odoo13_addon_stock_picking_manual_package-13.0.1.1.0.dist-info/WHEEL
odoo13_addon_stock_picking_manual_package-13.0.1.1.0.dist-info/top_level.txt
odoo13_addon_stock_picking_manual_package-13.0.1.1.0.dist-info/RECORD
